RestoDivisao/__init__.py
RestoDivisao/div5.py
RestoDivisao-0.0.1.dist-info/METADATA
RestoDivisao-0.0.1.dist-info/WHEEL
RestoDivisao-0.0.1.dist-info/top_level.txt
RestoDivisao-0.0.1.dist-info/RECORD
