Metadata-Version: 2.1
Name: RestoDivisao
Version: 0.0.1
Summary: Resto da divisão
Home-page: https://github.com/ljsmonteiro/simple-package-template
Author: lucio
Author-email: ljsmonteiro@gmail.com
License: UNKNOWN
Platform: UNKNOWN
Requires-Python: >=3.5
